pyCIAP/__init__.py
pyCIAP/ciap_mdt.py
pyCIAP/dsur.py
pyCIAP/dsur_cy.cpython-39-darwin.so
pyCIAP-0.0.2.dist-info/METADATA
pyCIAP-0.0.2.dist-info/WHEEL
pyCIAP-0.0.2.dist-info/top_level.txt
pyCIAP-0.0.2.dist-info/RECORD
