Metadata-Version: 2.1
Name: pyCIAP
Version: 0.0.2
Summary: A simple package the solve CIAPs with dwell time constraints
Home-page: https://github.com/jhelgert/pyCIAP
Author: Jonathan Helgert
Author-email: jhelgert@mail.uni-mannheim.de
License: UNKNOWN
Platform: UNKNOWN
Classifier: Programming Language :: Python :: 3.7
Classifier: Programming Language :: Python :: 3.7
Classifier: Programming Language :: Python :: 3.8
Classifier: Programming Language :: Python :: 3.9
Classifier: License :: OSI Approved :: MIT License
Classifier: Operating System :: OS Independent
Requires-Python: >=3.6
Requires-Dist: numpy
